iterutil/__init__.py
iterutil/__init__.pyi
iterutil-0.1.2.dist-info/licenses/LICENSE
iterutil-0.1.2.dist-info/METADATA
iterutil-0.1.2.dist-info/WHEEL
iterutil-0.1.2.dist-info/top_level.txt
iterutil-0.1.2.dist-info/RECORD
