Metadata-Version: 2.4
Name: iterutil
Version: 0.1.2
Summary: A simple iterator wrapper for rust-style iterator chaining
Author-email: Luke Scherrer <lukescherrer2@gmail.com>
License-Expression: MIT
Project-URL: Homepage, https://github.com/lscherrer2/iterutil
Project-URL: Issues, https://github.com/lscherrer2/iterutil/issues
Classifier: Programming Language :: Python :: 3
Classifier: Operating System :: OS Independent
Requires-Python: >=3.13
License-File: LICENSE
Dynamic: license-file
